{
  "task_type": "triage",
  "task_id": "2240",
  "started_at": "2026-02-23T15:49:27",
  "finished_at": "2026-02-23T15:50:40",
  "attempts": [
    {
      "agent": "codex",
      "task": "triage",
      "success": false,
      "result": null,
      "raw_output": "",
      "errors": "Agent returned None",
      "files_modified": [],
      "build_result": null,
      "test_result": null,
      "timed_out": false,
      "diff_summary": null,
      "timestamp": "2026-02-23T15:49:27"
    },
    {
      "agent": "gemini",
      "task": "triage",
      "success": true,
      "result": {
        "decision": "implement",
        "reason": "The current URL construction logic in HTTPBase.cs can result in double port numbers if a port is embedded in the hostname field and also specified in the port field.",
        "priority": "P2-bug",
        "estimated_files": [
          "mRemoteNG\\Connection\\Protocol\\Http\\Connection.Protocol.HTTPBase.cs"
        ],
        "approach": "Refactor the GetUrl() method in HTTPBase.cs to use UriBuilder for robust URL construction, correctly handling embedded ports in the hostname and prioritizing explicit port field values while avoiding double-port issues."
      },
      "raw_output": "```json\n{\n  \"decision\": \"implement\",\n  \"reason\": \"The current URL construction logic in HTTPBase.cs can result in double port numbers if a port is embedded in the hostname field and also specified in the port field.\",\n  \"priority\": \"P2-bug\",\n  \"estimated_files\": [\"mRemoteNG\\\\Connection\\\\Protocol\\\\Http\\\\Connection.Protocol.HTTPBase.cs\"],\n  \"approach\": \"Refactor the GetUrl() method in HTTPBase.cs to use UriBuilder for robust URL construction, correctly handling embedded ports in the hostname and prioritizing explicit port field values while avoiding double-port issues.\"\n}\n```\n",
      "errors": null,
      "files_modified": [],
      "build_result": null,
      "test_result": null,
      "timed_out": false,
      "diff_summary": null,
      "timestamp": "2026-02-23T15:50:40"
    }
  ],
  "timeout_count": 0,
  "all_timed_out": false,
  "final_success": true
}
